oamp_apibase/__init__.py
oamp_apibase/client.py
oamp_apibase-0.1.0.dist-info/LICENSE.md
oamp_apibase-0.1.0.dist-info/METADATA
oamp_apibase-0.1.0.dist-info/WHEEL
oamp_apibase-0.1.0.dist-info/RECORD
