Metadata-Version: 2.3
Name: oamp-apibase
Version: 0.1.0
Summary: 
License: MIT
Author: Mike Simkins
Author-email: software@g7software.dev
Requires-Python: >=3.11
Classifier: License :: OSI Approved :: MIT License
Classifier: Programming Language :: Python :: 3
Classifier: Programming Language :: Python :: 3.11
Classifier: Programming Language :: Python :: 3.12
Classifier: Programming Language :: Python :: 3.13
Requires-Dist: httpx[brotli,http2,socks,zstd] (>=0.28.1,<0.29.0)
